ky3m/__init__.py
ky3m/__main__.py
ky3m/cli.py
ky3m/common/__init__.py
ky3m/common/latin.py
ky3m/common/paths.py
ky3m/common/singleton.py
ky3m/common/str_base.py
ky3m/methods.py
ky3m/report.py
ky3m/services/__init__.py
ky3m/services/bundler.py
ky3m/services/extractor.py
ky3m/services/jar_keeper.py
ky3m/services/mcmod.py
ky3m/services/mm_storage.py
ky3m/services/pickler.py
ky3m-0.2.2.dist-info/LICENSE
ky3m-0.2.2.dist-info/WHEEL
ky3m-0.2.2.dist-info/METADATA
ky3m-0.2.2.dist-info/RECORD
