Metadata-Version: 2.1
Name: ky3m
Version: 0.2.2
Summary: Minecraft Mod Manager by Leon "Procybit" Shepelev
Home-page: https://github.com/Procybit/Ky3M
License: MIT
Keywords: minecraft
Author: Leon "Procybit" Shepelev
Author-email: kyleusnaff@gmail.com
Requires-Python: >=3.10,<4.0
Classifier: License :: OSI Approved :: MIT License
Classifier: Programming Language :: Python :: 3
Classifier: Programming Language :: Python :: 3.10
Requires-Dist: toml (>=0.10,<0.11)
Project-URL: Repository, https://github.com/Procybit/Ky3M
Project-URL: Report a bug!, https://github.com/Procybit/Ky3M/issues
